agently_stage/EventEmitter.py
agently_stage/Events.py
agently_stage/LICENSE
agently_stage/Stage.py
agently_stage/StageDispatch.py
agently_stage/StageException.py
agently_stage/StageFunction.py
agently_stage/StageHybridGenerator.py
agently_stage/StageResponse.py
agently_stage/Tunnel.py
agently_stage/__init__.py
agently_stage-0.2.0rc20250206.dist-info/LICENSE
agently_stage-0.2.0rc20250206.dist-info/METADATA
agently_stage-0.2.0rc20250206.dist-info/WHEEL
agently_stage-0.2.0rc20250206.dist-info/RECORD
