Metadata-Version: 2.3
Name: agently-stage
Version: 0.2.0rc20250206
Summary: Agently Stage - Efficient Convenient Asynchronous and Multithreaded Programming
License: Apache-2.0
Keywords: agently,async,multithreading,EventEmitter
Author: Agently Team
Author-email: developer@agently.tech
Requires-Python: >=3.9
Classifier: License :: OSI Approved :: Apache Software License
Classifier: Programming Language :: Python :: 3
Classifier: Programming Language :: Python :: 3.9
Classifier: Programming Language :: Python :: 3.10
Classifier: Programming Language :: Python :: 3.11
Classifier: Programming Language :: Python :: 3.12
Classifier: Programming Language :: Python :: 3.13
